
{
	"data": [		
		{
			"id": "1001",
			"name": "Snake",
			"image": "snake.png",
			"category": "Matematicas",
			"status": "SIN HACER",
			"rating": 0,
			"url": "/snake"
		},
        {
			"id": "1002",
			"name": "Memorama",
			"image": "memorama.jpg",
			"category": "Matematicas",
			"status": "SIN HACER",
			"rating": 0,
			"url": "/memoMate"
		},
        {
			"id": "1003",
			"name": "Rompecabezas",
			"image": "rompecabezas.jpg",
			"category": "Matematicas",
			"status": "SIN HACER",
			"rating": 0,
			"url": "/rompeMate"
		},
        {
			"id": "1004",
			"name": "Sudoku",
			"image": "sudoku.jpg",
			"category": "Matematicas",
			"status": "SIN HACER",
			"rating": 0,
			"url": "/sudoku"
		},
        {
			"id": "1000",
			"name": "Puzzle deslizable",
			"image": "sumasResta.jpg",
			"category": "Matematicas",
			"status": "SIN HACER",
			"rating": 0,
			"url": "/slidin"
		}
	]
}
